__builtins__.pyi
_boot.pyi
_espnow.pyi
_onewire.pyi
_thread.pyi
aioespnow.pyi
apa106.pyi
binascii.pyi
btree.pyi
cmath.pyi
cryptolib.pyi
deflate.pyi
dht.pyi
ds18x20.pyi
errno.pyi
esp.pyi
esp32.pyi
espnow.pyi
flashbdev.pyi
framebuf.pyi
gc.pyi
hashlib.pyi
heapq.pyi
inisetup.pyi
machine.pyi
math.pyi
micropython.pyi
mip/__init__.pyi
neopixel.pyi
network.pyi
ntptime.pyi
onewire.pyi
platform.pyi
random.pyi
requests/__init__.pyi
select.pyi
socket.pyi
time.pyi
tls.pyi
uarray.pyi
uasyncio.pyi
ubinascii.pyi
ubluetooth.pyi
ucollections.pyi
ucryptolib.pyi
uctypes.pyi
uerrno.pyi
uhashlib.pyi
uheapq.pyi
uio.pyi
ujson.pyi
umachine.pyi
umqtt/__init__.pyi
umqtt/robust.pyi
umqtt/simple.pyi
uos.pyi
uplatform.pyi
upysh.pyi
urandom.pyi
ure.pyi
urequests.pyi
uselect.pyi
usocket.pyi
ussl.pyi
ustruct.pyi
usys.pyi
utime.pyi
uwebsocket.pyi
uzlib.pyi
vfs.pyi
webrepl.pyi
webrepl_setup.pyi
websocket.pyi
micropython_esp32_esp32_generic_s2_stubs-1.27.0.post1.dist-info/LICENSE.md
micropython_esp32_esp32_generic_s2_stubs-1.27.0.post1.dist-info/METADATA
micropython_esp32_esp32_generic_s2_stubs-1.27.0.post1.dist-info/WHEEL
micropython_esp32_esp32_generic_s2_stubs-1.27.0.post1.dist-info/RECORD
